Metadata-Version: 2.1
Name: sentry-googlechat
Version: 10.0.0
Summary: A Sentry plugin which posts notifications to Google Chat (https://gsuite.google.com/products/chat/).
Home-page: https://github.com/jweslley/sentry-googlechat
Author: Jonhnny Weslley
Author-email: jw@jonhnnyweslley.net
License: MIT
Platform: UNKNOWN
Classifier: Intended Audience :: Developers
Classifier: Intended Audience :: System Administrators
Classifier: License :: OSI Approved :: MIT License
Classifier: Operating System :: OS Independent
Classifier: Topic :: Software Development
Classifier: Topic :: System :: Monitoring
